[
    {
        "name": "YouTube",
        "list": [
            "why_are_you_gay"
        ]
    },
    {
        "name": "Twitch",
        "list": [
            "kekw"
        ]
    },
    {
        "name": "Tiktok",
        "list": [
            "tajka_lyduna"
        ]
    },
    {
        "name": "Film",
        "list": [
            "everyone_in_this_room_is_now_dummer"
        ]
    },
    {
        "name": "Games",
        "list": [
            "here_we_go_again"
        ]
    },
    {
        "name": "Gachi",
        "list": [
            "ass_we_can"
        ]
    },
    {
        "name": "Slonik",
        "list": [
            "kyrluk"
        ]
    }
]
